archisound/__init__.py
archisound/archisound.py
archisound-0.0.6.dist-info/LICENSE
archisound-0.0.6.dist-info/METADATA
archisound-0.0.6.dist-info/WHEEL
archisound-0.0.6.dist-info/top_level.txt
archisound-0.0.6.dist-info/RECORD
