Metadata-Version: 2.1
Name: archisound
Version: 0.0.6
Summary: ArchiSound
Home-page: https://github.com/archinetai/archisound
Author: Flavio Schneider
Author-email: archinetai@protonmail.com
License: MIT
Keywords: artificial intelligence,deep learning
Classifier: Development Status :: 4 - Beta
Classifier: Intended Audience :: Developers
Classifier: Topic :: Scientific/Engineering :: Artificial Intelligence
Classifier: License :: OSI Approved :: MIT License
Classifier: Programming Language :: Python :: 3.6
License-File: LICENSE
Requires-Dist: torch (>=1.6)
Requires-Dist: data-science-types (>=0.2)
Requires-Dist: transformers
Requires-Dist: audio-diffusion-pytorch
Requires-Dist: audio-encoders-pytorch
